dbx/__init__.py
dbx/__main__.py
dbx/_version.py
dbx/callbacks.py
dbx/cli.py
dbx/constants.py
dbx/custom.py
dbx/options.py
dbx/types.py
dbx/api/__init__.py
dbx/api/_module_loader.py
dbx/api/auth.py
dbx/api/build.py
dbx/api/client_provider.py
dbx/api/cluster.py
dbx/api/config_reader.py
dbx/api/configure.py
dbx/api/context.py
dbx/api/deployment.py
dbx/api/destroyer.py
dbx/api/execute.py
dbx/api/jinja.py
dbx/api/output_provider.py
dbx/api/adjuster/__init__.py
dbx/api/adjuster/adjuster.py
dbx/api/adjuster/policy.py
dbx/api/adjuster/mixins/__init__.py
dbx/api/adjuster/mixins/base.py
dbx/api/adjuster/mixins/existing_cluster.py
dbx/api/adjuster/mixins/file_reference.py
dbx/api/adjuster/mixins/instance_pool.py
dbx/api/adjuster/mixins/instance_profile.py
dbx/api/adjuster/mixins/pipeline.py
dbx/api/adjuster/mixins/service_principal.py
dbx/api/adjuster/mixins/sql_properties.py
dbx/api/dependency/__init__.py
dbx/api/dependency/core_package.py
dbx/api/dependency/requirements.py
dbx/api/launch/__init__.py
dbx/api/launch/contexts.py
dbx/api/launch/functions.py
dbx/api/launch/pipeline_models.py
dbx/api/launch/processors.py
dbx/api/launch/tracer.py
dbx/api/launch/runners/__init__.py
dbx/api/launch/runners/asset_based.py
dbx/api/launch/runners/base.py
dbx/api/launch/runners/pipeline.py
dbx/api/launch/runners/standard.py
dbx/api/services/__init__.py
dbx/api/services/_base.py
dbx/api/services/jobs.py
dbx/api/services/permissions.py
dbx/api/services/pipelines.py
dbx/api/storage/__init__.py
dbx/api/storage/io.py
dbx/api/storage/mlflow_based.py
dbx/commands/__init__.py
dbx/commands/configure.py
dbx/commands/deploy.py
dbx/commands/destroy.py
dbx/commands/execute.py
dbx/commands/init.py
dbx/commands/launch.py
dbx/commands/version.py
dbx/commands/sync/__init__.py
dbx/commands/sync/functions.py
dbx/commands/sync/options.py
dbx/commands/sync/sync.py
dbx/models/__init__.py
dbx/models/build.py
dbx/models/deployment.py
dbx/models/validators.py
dbx/models/cli/__init__.py
dbx-0.8.19.dist-info/METADATA
dbx-0.8.19.dist-info/WHEEL
dbx-0.8.19.dist-info/entry_points.txt
dbx-0.8.19.dist-info/licenses/LICENSE
dbx-0.8.19.dist-info/licenses/NOTICE
dbx-0.8.19.dist-info/RECORD
