Metadata-Version: 2.3
Name: dbx
Version: 0.8.19
Summary: DataBricks CLI eXtensions aka dbx
Author: Michael Shtelma, Thunder Shiviah
Author-email: Ivan Trusov <ivan.trusov@databricks.com>
License-File: LICENSE
License-File: NOTICE
Classifier: Intended Audience :: Developers
Classifier: Intended Audience :: System Administrators
Requires-Python: >=3.8
Requires-Dist: aiohttp>=3.8.2
Requires-Dist: click<9.0.0,>=8.1.0
Requires-Dist: cookiecutter<3.0.0,>2.1.0
Requires-Dist: cryptography>=42.0.8
Requires-Dist: databricks-cli<0.18,>=0.17
Requires-Dist: jinja2>=2.11.2
Requires-Dist: mlflow-skinny<3.0.0,>=2.0.0
Requires-Dist: pathspec>=0.9.0
Requires-Dist: pydantic<2.0.0,>=1.10.8
Requires-Dist: pyyaml>=6.0
Requires-Dist: requests<3.0.0,>=2.30.1
Requires-Dist: rich<=13.0.0,>=12.6.0
Requires-Dist: tenacity<9.0.0,>=8.2.2
Requires-Dist: typer[all]==0.7.0
Requires-Dist: watchdog>=2.1.0
Provides-Extra: aws
Requires-Dist: boto3<2,>=1.26.13; extra == 'aws'
Provides-Extra: azure
Requires-Dist: azure-identity<2.0.0,>=1.12.0; extra == 'azure'
Requires-Dist: azure-storage-blob<13.0.0,>=12.14.1; extra == 'azure'
Provides-Extra: gcp
Requires-Dist: google-cloud-storage<3.0.0,>=2.6.0; extra == 'gcp'
